pyframe/__init__.py
pyframe/__main__.py
pyframe/models/__init__.py
pyframe/models/alert.py
pyframe/models/arbitration.py
pyframe/models/archon_hunt.py
pyframe/models/cambion_cycle.py
pyframe/models/cetus_cycle.py
pyframe/models/common.py
pyframe/models/conclave_challenge.py
pyframe/models/construction_progress.py
pyframe/models/daily_deal.py
pyframe/models/dark_sector.py
pyframe/models/earth_cycle.py
pyframe/models/event.py
pyframe/models/fissure.py
pyframe/models/flash_sale.py
pyframe/models/global_upgrade.py
pyframe/models/invasion.py
pyframe/models/kuva.py
pyframe/models/news.py
pyframe/models/nightwave.py
pyframe/models/persistent_enemy.py
pyframe/models/simaris.py
pyframe/models/sortie.py
pyframe/models/steel_path.py
pyframe/models/syndicate_mission.py
pyframe/models/vallis_cycle.py
pyframe/models/void_trader.py
pyframe/models/worldstate.py
python_PyFrame-1.0.6.dist-info/LICENSE
python_PyFrame-1.0.6.dist-info/METADATA
python_PyFrame-1.0.6.dist-info/WHEEL
python_PyFrame-1.0.6.dist-info/top_level.txt
python_PyFrame-1.0.6.dist-info/RECORD
