Metadata-Version: 2.1
Name: python-PyFrame
Version: 1.0.6
Summary: A simple python API wrapper for api.warframestat.us
Home-page: https://github.com/LilTOJustice/PyFrame
Author: LilTOJustice
Author-email: muianick4@gmail.com
License: GNU GENERAL PUBLIC LICENSE
Requires-Python: >=3.6
License-File: LICENSE
